appsflyer/__init__.py
appsflyer/rest/__init__.py
appsflyer-0.1.0.dist-info/LICENSE
appsflyer-0.1.0.dist-info/METADATA
appsflyer-0.1.0.dist-info/WHEEL
appsflyer-0.1.0.dist-info/top_level.txt
appsflyer-0.1.0.dist-info/RECORD
