Metadata-Version: 2.1
Name: appsflyer
Version: 0.1.0
Summary: AppsFlyer S2S events API client
Home-page: https://github.com/fredericojordan/appsflyer-python/
Author: Frederico Jordan
Author-email: fredericojordan@gmail.com
License: UNKNOWN
Keywords: appsflyer
Platform: UNKNOWN
Classifier: Development Status :: 2 - Pre-Alpha
Classifier: Intended Audience :: Developers
Classifier: License :: OSI Approved :: MIT License
Classifier: Operating System :: OS Independent
Classifier: Programming Language :: Python
Classifier: Programming Language :: Python :: 3
Requires-Dist: requests (>=2.0.0)
